{
  "timestamp": "2026-01-30T11:45:04.067604",
  "l1": {
    "time": "2026-01-30 11:42:00",
    "speed": 543.0,
    "density": 1.04,
    "bt": 3.01,
    "bz_gsm": 0.21,
    "pressure_dyn": 0.5128910148960001
  },
  "goes": {
    "G19": {
      "time": "2026-01-30 11:42:00+00:00",
      "Hp": 88.80596160888672,
      "B_total": 98.61373901367188,
      "mlt": 2.5999999999999996,
      "mlt_sector": "NIGHT"
    },
    "G18": {
      "time": "2026-01-30 11:42:00+00:00",
      "Hp": 73.22563934326172,
      "B_total": 75.68802642822266,
      "mlt": 2.5999999999999996,
      "mlt_sector": "NIGHT"
    }
  },
  "detections": {
    "ip_shocks": [],
    "ssc_events": []
  },
  "published_at": "2026-01-30T11:45:34.495658Z"
}