{
  "timestamp": "2026-05-30T02:30:23.439869",
  "l1": {
    "time": "2026-05-30 02:27:00",
    "speed": 411.4,
    "density": 1.12,
    "bt": 8.55,
    "bz_gsm": -1.33,
    "pressure_dyn": 0.31705798106752003
  },
  "goes": {
    "G19": {
      "time": "2026-05-30 02:28:00+00:00",
      "Hp": 69.58849334716797,
      "B_total": 129.0534210205078,
      "mlt": 17.366666666666667,
      "mlt_sector": "DUSK"
    }
  },
  "tec": {
    "time": "2026-05-30T02:05:00Z",
    "global_mean_tec": 17.395036790554805,
    "anom_max_abs": 18.03570716994419,
    "anom_rms": 3.1480833746253105,
    "threat_belt_anom_mean": 0.3653151465682402,
    "quality_pct": 72.16435185185185
  },
  "detections": {
    "ip_shocks": [],
    "ssc_events": []
  },
  "published_at": "2026-05-30T02:31:05.807632Z"
}