{
  "timestamp": "2026-05-27T14:30:20.964454",
  "l1": {
    "time": "2026-05-27 14:27:00",
    "speed": 385.1,
    "density": 3.8,
    "bt": 6.25,
    "bz_gsm": -5.12,
    "pressure_dyn": 0.9425897793188001
  },
  "goes": {
    "G19": {
      "time": "2026-05-27 14:28:00+00:00",
      "Hp": 104.16802215576172,
      "B_total": 110.36343383789062,
      "mlt": 5.366666666666667,
      "mlt_sector": "DAWN"
    },
    "G18": {
      "time": "2026-05-27 14:27:00+00:00",
      "Hp": 87.2382583618164,
      "B_total": 92.04143524169922,
      "mlt": 5.35,
      "mlt_sector": "DAWN"
    }
  },
  "tec": {
    "time": "2026-05-27T14:05:00Z",
    "global_mean_tec": 18.616475524916414,
    "anom_max_abs": 14.001709489440994,
    "anom_rms": 2.671248361590273,
    "threat_belt_anom_mean": 2.148764564308575,
    "quality_pct": 72.80092592592592
  },
  "detections": {
    "ip_shocks": [],
    "ssc_events": []
  },
  "published_at": "2026-05-27T14:31:00.226852Z"
}