{
  "timestamp": "2026-01-07T23:45:03.973772",
  "l1": {
    "time": "2026-01-07 23:41:00",
    "speed": 348.1,
    "density": 6.26,
    "bt": 10.31,
    "bz_gsm": -8.59,
    "pressure_dyn": 1.2687453753383602
  },
  "goes": {
    "G19": {
      "time": "2026-01-07 23:43:00+00:00",
      "Hp": 56.87241744995117,
      "B_total": 67.20997619628906,
      "mlt": 14.616666666666665,
      "mlt_sector": "NOON"
    },
    "G18": {
      "time": "2026-01-07 23:43:00+00:00",
      "Hp": 111.09569549560547,
      "B_total": 113.43765258789062,
      "mlt": 14.616666666666665,
      "mlt_sector": "NOON"
    }
  },
  "detections": {
    "ip_shocks": [],
    "ssc_events": []
  },
  "published_at": "2026-01-07T23:45:58.254283Z"
}