{
  "timestamp": "2026-05-14T22:30:04.066678",
  "l1": {
    "time": "2026-05-14 22:26:00",
    "speed": 401.0,
    "density": 4.11,
    "bt": 4.71,
    "bz_gsm": -3.52,
    "pressure_dyn": 1.1054081431860001
  },
  "goes": {
    "G19": {
      "time": "2026-05-14 22:28:00+00:00",
      "Hp": 102.52704620361328,
      "B_total": 110.2359390258789,
      "mlt": 13.366666666666665,
      "mlt_sector": "NOON"
    },
    "G18": {
      "time": "2026-05-14 22:27:00+00:00",
      "Hp": 122.36468505859375,
      "B_total": 124.3919906616211,
      "mlt": 13.35,
      "mlt_sector": "NOON"
    }
  },
  "tec": {},
  "detections": {
    "ip_shocks": [],
    "ssc_events": []
  },
  "published_at": "2026-05-14T22:30:56.357933Z"
}