{
  "timestamp": "2026-05-21T09:20:04.134457",
  "l1": {
    "time": "2026-05-21 09:17:00",
    "speed": 414.3,
    "density": 0.99,
    "bt": 4.03,
    "bz_gsm": 0.21,
    "pressure_dyn": 0.28422164823426005
  },
  "goes": {
    "G19": {
      "time": "2026-05-21 09:17:00+00:00",
      "Hp": 89.05492401123047,
      "B_total": 101.36027526855469,
      "mlt": 0.18333333333333357,
      "mlt_sector": "NIGHT"
    },
    "G18": {
      "time": "2026-05-21 09:18:00+00:00",
      "Hp": 79.18370819091797,
      "B_total": 84.73747253417969,
      "mlt": 0.20000000000000107,
      "mlt_sector": "NIGHT"
    }
  },
  "tec": {
    "time": "2026-05-21T08:55:00Z",
    "global_mean_tec": 18.862997142480577,
    "anom_max_abs": 18.70290622989456,
    "anom_rms": 3.923455555651344,
    "threat_belt_anom_mean": -1.2763749728947216,
    "quality_pct": 72.64660493827161
  },
  "detections": {
    "ip_shocks": [],
    "ssc_events": []
  },
  "published_at": "2026-05-21T09:20:45.709856Z"
}