{
  "timestamp": "2026-05-26T17:40:04.068869",
  "l1": {
    "time": "2026-05-26 17:38:00",
    "speed": 386.3,
    "density": 2.84,
    "bt": null,
    "bz_gsm": null,
    "pressure_dyn": 0.7088589853949601
  },
  "goes": {
    "G19": {
      "time": "2026-05-26 17:37:00+00:00",
      "Hp": 118.64930725097656,
      "B_total": 123.51860046386719,
      "mlt": 8.516666666666667,
      "mlt_sector": "DAWN"
    },
    "G18": {
      "time": "2026-05-26 17:38:00+00:00",
      "Hp": 113.57121276855469,
      "B_total": 116.92302703857422,
      "mlt": 8.533333333333333,
      "mlt_sector": "DAWN"
    }
  },
  "tec": {
    "time": "2026-05-26T17:05:00Z",
    "global_mean_tec": 18.08009657856626,
    "anom_max_abs": 18.460926864195947,
    "anom_rms": 3.348860640542949,
    "threat_belt_anom_mean": 3.456163294392791,
    "quality_pct": 73.57253086419753
  },
  "detections": {
    "ip_shocks": [],
    "ssc_events": []
  },
  "published_at": "2026-05-26T17:40:36.382288Z"
}