{
  "timestamp": "2026-05-28T05:30:14.555997",
  "l1": {
    "time": "2026-05-28 05:27:00",
    "speed": 378.7,
    "density": 6.13,
    "bt": 8.44,
    "bz_gsm": -6.73,
    "pressure_dyn": 1.47042601329022
  },
  "goes": {
    "G18": {
      "time": "2026-05-28 05:27:00+00:00",
      "Hp": 57.190616607666016,
      "B_total": 65.79756164550781,
      "mlt": 20.35,
      "mlt_sector": "DUSK"
    }
  },
  "tec": {},
  "detections": {
    "ip_shocks": [],
    "ssc_events": []
  },
  "published_at": "2026-05-28T05:30:56.390891Z"
}