{
  "timestamp": "2026-05-21T02:50:03.788198",
  "l1": {
    "time": "2026-05-21 02:46:00",
    "speed": 456.9,
    "density": 1.76,
    "bt": 4.85,
    "bz_gsm": -3.2,
    "pressure_dyn": 0.61453564213536
  },
  "goes": {
    "G19": {
      "time": "2026-05-21 02:47:00+00:00",
      "Hp": 86.07071685791016,
      "B_total": 103.20819854736328,
      "mlt": 17.683333333333334,
      "mlt_sector": "DUSK"
    },
    "G18": {
      "time": "2026-05-21 02:48:00+00:00",
      "Hp": 90.98112487792969,
      "B_total": 94.8636474609375,
      "mlt": 17.7,
      "mlt_sector": "DUSK"
    }
  },
  "tec": {
    "time": "2026-05-21T02:25:00Z",
    "global_mean_tec": 17.055311979336235,
    "anom_max_abs": 14.448308851153541,
    "anom_rms": 3.5833545000788116,
    "threat_belt_anom_mean": -2.476296287641971,
    "quality_pct": 73.2253086419753
  },
  "detections": {
    "ip_shocks": [],
    "ssc_events": []
  },
  "published_at": "2026-05-21T02:50:51.899343Z"
}