{
  "timestamp": "2026-07-14T09:30:43.124433",
  "l1": {
    "time": "2026-07-14 09:25:00",
    "speed": 362.3,
    "density": 1.83,
    "bt": 8.48,
    "bz_gsm": -0.34,
    "pressure_dyn": 0.40177216958682005
  },
  "goes": {
    "G18": {
      "time": "2026-07-14 11:20:00+00:00",
      "Hp": 80.04678344726562,
      "B_total": 84.65538787841797,
      "mlt": 2.1866666666666674,
      "mlt_sector": "NIGHT"
    }
  },
  "tec": {
    "time": "2026-07-14T11:05:00Z",
    "global_mean_tec": 16.64713177286828,
    "anom_max_abs": 12.505197308077655,
    "anom_rms": 2.874476266329703,
    "threat_belt_anom_mean": -3.3823488452504202,
    "quality_pct": 71.04552469135803
  },
  "detections": {
    "ip_shocks": [],
    "ssc_events": []
  },
  "published_at": "2026-07-14T11:31:28.423682Z"
}