{
  "timestamp": "2026-05-22T16:10:04.076151",
  "l1": {
    "time": "2026-05-22 16:06:00",
    "speed": 340.2,
    "density": 1.07,
    "bt": 3.08,
    "bz_gsm": -0.91,
    "pressure_dyn": 0.20713070753928
  },
  "goes": {
    "G19": {
      "time": "2026-05-22 16:07:00+00:00",
      "Hp": 107.1630630493164,
      "B_total": 113.36541748046875,
      "mlt": 7.0166666666666675,
      "mlt_sector": "DAWN"
    },
    "G18": {
      "time": "2026-05-22 16:08:00+00:00",
      "Hp": 99.1195068359375,
      "B_total": 102.72796630859375,
      "mlt": 7.033333333333333,
      "mlt_sector": "DAWN"
    }
  },
  "tec": {
    "time": "2026-05-22T15:45:00Z",
    "global_mean_tec": 17.01307365148106,
    "anom_max_abs": 14.76067260815071,
    "anom_rms": 3.0726905431203284,
    "threat_belt_anom_mean": -0.61816710423285,
    "quality_pct": 71.33487654320987
  },
  "detections": {
    "ip_shocks": [],
    "ssc_events": []
  },
  "published_at": "2026-05-22T16:10:45.001225Z"
}