{
  "timestamp": "2026-01-13T15:15:04.016281",
  "l1": {
    "time": "2026-01-13 14:37:00",
    "speed": 503.0,
    "density": 0.22,
    "bt": null,
    "bz_gsm": null,
    "pressure_dyn": 0.093100227748
  },
  "goes": {
    "G19": {
      "time": "2026-01-13 15:13:00+00:00",
      "Hp": 93.96435546875,
      "B_total": 102.36195373535156,
      "mlt": 6.116666666666667,
      "mlt_sector": "DAWN"
    },
    "G18": {
      "time": "2026-01-13 15:13:00+00:00",
      "Hp": 87.02631378173828,
      "B_total": 89.58787536621094,
      "mlt": 6.116666666666667,
      "mlt_sector": "DAWN"
    }
  },
  "detections": {
    "ip_shocks": [],
    "ssc_events": []
  },
  "published_at": "2026-01-13T15:15:43.660702Z"
}