{
  "timestamp": "2026-07-01T22:30:31.764084",
  "l1": {},
  "goes": {
    "G18": {
      "time": "2026-07-01 22:27:00+00:00",
      "Hp": 121.79256439208984,
      "B_total": 124.36729431152344,
      "mlt": 13.35,
      "mlt_sector": "NOON"
    },
    "G19": {
      "time": "2026-07-01 22:27:00+00:00",
      "Hp": 104.90614318847656,
      "B_total": 115.3244400024414,
      "mlt": 13.35,
      "mlt_sector": "NOON"
    }
  },
  "tec": {
    "time": "2026-07-01T22:05:00Z",
    "global_mean_tec": 15.041965131182922,
    "anom_max_abs": 9.22020664962028,
    "anom_rms": 1.6521662886821415,
    "threat_belt_anom_mean": 0.4486451170387081,
    "quality_pct": 73.66898148148148
  },
  "detections": {
    "ip_shocks": [],
    "ssc_events": []
  },
  "published_at": "2026-07-01T22:30:35.576902Z"
}