{
  "timestamp": "2026-06-02T03:20:28.864767",
  "l1": {
    "time": "2026-06-02 03:17:00",
    "speed": 393.6,
    "density": 1.83,
    "bt": 6.04,
    "bz_gsm": 0.55,
    "pressure_dyn": 0.4741910597836801
  },
  "goes": {
    "G19": {
      "time": "2026-06-02 04:08:00+00:00",
      "Hp": 61.0600471496582,
      "B_total": 94.71759033203125,
      "mlt": 19.033333333333335,
      "mlt_sector": "DUSK"
    },
    "G18": {
      "time": "2026-06-02 04:09:00+00:00",
      "Hp": 68.2152099609375,
      "B_total": 76.62577819824219,
      "mlt": 19.05,
      "mlt_sector": "DUSK"
    }
  },
  "tec": {
    "time": "2026-06-02T03:45:00Z",
    "global_mean_tec": 17.498897135279034,
    "anom_max_abs": 14.54439350377433,
    "anom_rms": 2.8838441837407323,
    "threat_belt_anom_mean": 0.2431147229926104,
    "quality_pct": 73.26388888888889
  },
  "detections": {
    "ip_shocks": [],
    "ssc_events": []
  },
  "published_at": "2026-06-02T04:20:22.064691Z"
}