{
  "timestamp": "2026-01-14T10:00:03.980568",
  "l1": {
    "time": "2026-01-14 09:57:00",
    "speed": 552.0,
    "density": 1.09,
    "bt": 5.65,
    "bz_gsm": 0.41,
    "pressure_dyn": 0.5555162223360001
  },
  "goes": {
    "G19": {
      "time": "2026-01-14 09:58:00+00:00",
      "Hp": 82.8135757446289,
      "B_total": 91.70934295654297,
      "mlt": 0.8666666666666671,
      "mlt_sector": "NIGHT"
    },
    "G18": {
      "time": "2026-01-14 09:58:00+00:00",
      "Hp": 76.3614273071289,
      "B_total": 79.64859771728516,
      "mlt": 0.8666666666666671,
      "mlt_sector": "NIGHT"
    }
  },
  "detections": {
    "ip_shocks": [],
    "ssc_events": []
  },
  "published_at": "2026-01-14T10:00:51.657724Z"
}