{
  "timestamp": "2026-01-07T06:30:03.991961",
  "l1": {
    "time": "2026-01-07 03:53:00",
    "speed": 352.6,
    "density": 1.95,
    "bt": null,
    "bz_gsm": null,
    "pressure_dyn": 0.40550043061320007
  },
  "goes": {
    "G19": {
      "time": "2026-01-07 06:27:00+00:00",
      "Hp": 79.41261291503906,
      "B_total": 84.9875259399414,
      "mlt": 21.35,
      "mlt_sector": "NIGHT"
    },
    "G18": {
      "time": "2026-01-07 06:27:00+00:00",
      "Hp": 86.6580581665039,
      "B_total": 88.95677947998047,
      "mlt": 21.35,
      "mlt_sector": "NIGHT"
    }
  },
  "detections": {
    "ip_shocks": [],
    "ssc_events": []
  },
  "published_at": "2026-01-07T06:30:27.446753Z"
}