{
  "timestamp": "2026-05-10T11:45:04.853450",
  "l1": {
    "time": "2026-05-10 11:42:00",
    "speed": 398.8,
    "density": 2.62,
    "bt": 3.71,
    "bz_gsm": 0.79,
    "pressure_dyn": 0.6969533068652801
  },
  "goes": {
    "G19": {
      "time": "2026-05-10 11:42:00+00:00",
      "Hp": 104.31980895996094,
      "B_total": 111.90718841552734,
      "mlt": 2.5999999999999996,
      "mlt_sector": "NIGHT"
    },
    "G18": {
      "time": "2026-05-10 11:43:00+00:00",
      "Hp": 89.92703247070312,
      "B_total": 94.56639862060547,
      "mlt": 2.616666666666667,
      "mlt_sector": "NIGHT"
    }
  },
  "detections": {
    "ip_shocks": [],
    "ssc_events": []
  },
  "published_at": "2026-05-10T11:45:57.987786Z"
}