{
  "timestamp": "2026-02-01T20:00:04.160660",
  "l1": {
    "time": "2026-02-01 19:57:00",
    "speed": 295.5,
    "density": 1.37,
    "bt": 4.49,
    "bz_gsm": -2.0,
    "pressure_dyn": 0.20009103470550002
  },
  "goes": {
    "G19": {
      "time": "2026-02-01 19:57:00+00:00",
      "Hp": 96.2417984008789,
      "B_total": 104.05217742919922,
      "mlt": 10.85,
      "mlt_sector": "NOON"
    },
    "G18": {
      "time": "2026-02-01 19:57:00+00:00",
      "Hp": 101.83292388916016,
      "B_total": 104.1534423828125,
      "mlt": 10.85,
      "mlt_sector": "NOON"
    }
  },
  "detections": {
    "ip_shocks": [],
    "ssc_events": []
  },
  "published_at": "2026-02-01T20:00:54.771251Z"
}