{
  "timestamp": "2026-05-28T15:10:17.093912",
  "l1": {
    "time": "2026-05-28 15:08:00",
    "speed": 414.1,
    "density": 3.62,
    "bt": 7.98,
    "bz_gsm": -4.86,
    "pressure_dyn": 1.0382719565337202
  },
  "goes": {
    "G19": {
      "time": "2026-05-28 15:09:00+00:00",
      "Hp": 111.23876190185547,
      "B_total": 116.04210662841797,
      "mlt": 6.050000000000001,
      "mlt_sector": "DAWN"
    },
    "G18": {
      "time": "2026-05-28 15:07:00+00:00",
      "Hp": 89.73517608642578,
      "B_total": 94.95355987548828,
      "mlt": 6.0166666666666675,
      "mlt_sector": "DAWN"
    }
  },
  "tec": {
    "time": "2026-05-28T14:45:00Z",
    "global_mean_tec": 18.491200251517565,
    "anom_max_abs": 15.070258041451272,
    "anom_rms": 2.595362120793138,
    "threat_belt_anom_mean": 2.049061283548478,
    "quality_pct": 73.53395061728395
  },
  "detections": {
    "ip_shocks": [],
    "ssc_events": []
  },
  "published_at": "2026-05-28T15:10:59.595061Z"
}