{
  "timestamp": "2026-05-27T11:50:20.958109",
  "l1": {
    "time": "2026-05-27 11:47:00",
    "speed": 403.5,
    "density": 2.26,
    "bt": 6.12,
    "bz_gsm": 6.07,
    "pressure_dyn": 0.615442678731
  },
  "goes": {
    "G19": {
      "time": "2026-05-27 11:48:00+00:00",
      "Hp": 92.96988677978516,
      "B_total": 101.93745422363281,
      "mlt": 2.700000000000001,
      "mlt_sector": "NIGHT"
    },
    "G18": {
      "time": "2026-05-27 11:48:00+00:00",
      "Hp": 73.47058868408203,
      "B_total": 81.41327667236328,
      "mlt": 2.700000000000001,
      "mlt_sector": "NIGHT"
    }
  },
  "tec": {},
  "detections": {
    "ip_shocks": [],
    "ssc_events": []
  },
  "published_at": "2026-05-27T11:51:01.392862Z"
}