{
  "timestamp": "2026-07-01T23:00:32.655678",
  "l1": {},
  "goes": {
    "G18": {
      "time": "2026-07-01 22:57:00+00:00",
      "Hp": 114.96699523925781,
      "B_total": 117.3224105834961,
      "mlt": 13.85,
      "mlt_sector": "NOON"
    },
    "G19": {
      "time": "2026-07-01 22:58:00+00:00",
      "Hp": 99.42010498046875,
      "B_total": 110.26329803466797,
      "mlt": 13.866666666666665,
      "mlt_sector": "NOON"
    }
  },
  "tec": {
    "time": "2026-07-01T22:25:00Z",
    "global_mean_tec": 14.92253777845719,
    "anom_max_abs": 10.252939370059252,
    "anom_rms": 1.6282091552203386,
    "threat_belt_anom_mean": 0.3341360812040028,
    "quality_pct": 73.57253086419753
  },
  "detections": {
    "ip_shocks": [],
    "ssc_events": []
  },
  "published_at": "2026-07-01T23:00:36.763590Z"
}