{
  "timestamp": "2026-06-08T19:20:22.202851",
  "l1": {
    "time": "2026-06-08 19:17:00",
    "speed": 459.7,
    "density": 1.27,
    "bt": 4.56,
    "bz_gsm": -1.64,
    "pressure_dyn": 0.44889505462618
  },
  "goes": {
    "G19": {
      "time": "2026-06-08 19:18:00+00:00",
      "Hp": 96.93646240234375,
      "B_total": 99.65535736083984,
      "mlt": 10.200000000000001,
      "mlt_sector": "NOON"
    },
    "G18": {
      "time": "2026-06-08 19:18:00+00:00",
      "Hp": 91.9205551147461,
      "B_total": 100.72491455078125,
      "mlt": 10.200000000000001,
      "mlt_sector": "NOON"
    }
  },
  "tec": {
    "time": "2026-06-08T18:55:00Z",
    "global_mean_tec": 15.184507575645215,
    "anom_max_abs": 14.873031137554882,
    "anom_rms": 2.7606262747042365,
    "threat_belt_anom_mean": -0.03489574512836344,
    "quality_pct": 73.88117283950618
  },
  "detections": {
    "ip_shocks": [],
    "ssc_events": []
  },
  "published_at": "2026-06-08T19:21:03.130403Z"
}