{
  "timestamp": "2026-06-28T08:30:31.086230",
  "l1": {
    "time": "2026-06-28 08:26:00",
    "speed": 476.3,
    "density": 6.51,
    "bt": 2.59,
    "bz_gsm": 0.96,
    "pressure_dyn": 2.4702120961379403
  },
  "goes": {
    "G18": {
      "time": "2026-06-28 08:28:00+00:00",
      "Hp": 77.80307006835938,
      "B_total": 83.66655731201172,
      "mlt": 23.366666666666667,
      "mlt_sector": "NIGHT"
    },
    "G19": {
      "time": "2026-06-28 08:29:00+00:00",
      "Hp": 82.70823669433594,
      "B_total": 97.55485534667969,
      "mlt": 23.383333333333333,
      "mlt_sector": "NIGHT"
    }
  },
  "tec": {
    "time": "2026-06-28T08:05:00Z",
    "global_mean_tec": 17.571322436120376,
    "anom_max_abs": 9.567727858691882,
    "anom_rms": 1.848268335353797,
    "threat_belt_anom_mean": 1.8731534217787662,
    "quality_pct": 72.12577160493827
  },
  "detections": {
    "ip_shocks": [],
    "ssc_events": []
  },
  "published_at": "2026-06-28T08:31:24.297051Z"
}