{
  "timestamp": "2026-06-27T03:10:16.874129",
  "l1": {
    "time": "2026-06-27 03:07:00",
    "speed": 480.1,
    "density": 1.84,
    "bt": 3.84,
    "bz_gsm": 0.09,
    "pressure_dyn": 0.7093708324398401
  },
  "goes": {
    "G18": {
      "time": "2026-06-27 03:08:00+00:00",
      "Hp": 85.99140930175781,
      "B_total": 89.97189331054688,
      "mlt": 18.03333333333333,
      "mlt_sector": "DUSK"
    },
    "G19": {
      "time": "2026-06-27 03:07:00+00:00",
      "Hp": 71.82254028320312,
      "B_total": 97.64633178710938,
      "mlt": 18.016666666666666,
      "mlt_sector": "DUSK"
    }
  },
  "tec": {
    "time": "2026-06-27T02:35:00Z",
    "global_mean_tec": 15.393062165031438,
    "anom_max_abs": 11.030836259243433,
    "anom_rms": 1.6556115858178742,
    "threat_belt_anom_mean": -0.23391307839953188,
    "quality_pct": 72.8395061728395
  },
  "detections": {
    "ip_shocks": [],
    "ssc_events": []
  },
  "published_at": "2026-06-27T03:10:58.712163Z"
}