{
  "timestamp": "2026-06-27T02:30:35.024420",
  "l1": {
    "time": "2026-06-27 02:26:00",
    "speed": 480.6,
    "density": 1.89,
    "bt": 3.87,
    "bz_gsm": -0.84,
    "pressure_dyn": 0.73016570290104
  },
  "goes": {
    "G18": {
      "time": "2026-06-27 02:28:00+00:00",
      "Hp": 77.8107681274414,
      "B_total": 83.85894775390625,
      "mlt": 17.366666666666667,
      "mlt_sector": "DUSK"
    },
    "G19": {
      "time": "2026-06-27 02:28:00+00:00",
      "Hp": 74.49851989746094,
      "B_total": 95.56378173828125,
      "mlt": 17.366666666666667,
      "mlt_sector": "DUSK"
    }
  },
  "tec": {
    "time": "2026-06-27T02:05:00Z",
    "global_mean_tec": 15.124317022777541,
    "anom_max_abs": 8.754604279373297,
    "anom_rms": 1.514840112718102,
    "threat_belt_anom_mean": 0.012936987892901132,
    "quality_pct": 72.22222222222223
  },
  "detections": {
    "ip_shocks": [],
    "ssc_events": []
  },
  "published_at": "2026-06-27T02:31:30.921667Z"
}