{
  "timestamp": "2026-06-09T06:00:17.402660",
  "l1": {
    "time": "2026-06-09 05:57:00",
    "speed": 464.9,
    "density": 2.9,
    "bt": 4.5,
    "bz_gsm": 0.35,
    "pressure_dyn": 1.0483569597853999
  },
  "goes": {
    "G19": {
      "time": "2026-06-09 05:57:00+00:00",
      "Hp": 69.93555450439453,
      "B_total": 74.63548278808594,
      "mlt": 20.85,
      "mlt_sector": "DUSK"
    },
    "G18": {
      "time": "2026-06-09 05:58:00+00:00",
      "Hp": 68.6800537109375,
      "B_total": 90.96351623535156,
      "mlt": 20.866666666666667,
      "mlt_sector": "DUSK"
    }
  },
  "tec": {
    "time": "2026-06-09T05:35:00Z",
    "global_mean_tec": 16.878273777384287,
    "anom_max_abs": 16.23488460207472,
    "anom_rms": 3.244140799890317,
    "threat_belt_anom_mean": -0.868181631100753,
    "quality_pct": 72.76234567901234
  },
  "detections": {
    "ip_shocks": [],
    "ssc_events": []
  },
  "published_at": "2026-06-09T06:01:06.132682Z"
}