{
  "timestamp": "2026-05-08T05:00:04.026089",
  "l1": {
    "time": "2026-05-08 04:58:00",
    "speed": 430.0,
    "density": 6.9,
    "bt": null,
    "bz_gsm": null,
    "pressure_dyn": 2.133919806
  },
  "goes": {
    "G19": {
      "time": "2026-05-08 04:58:00+00:00",
      "Hp": 68.43578338623047,
      "B_total": 92.03241729736328,
      "mlt": 19.866666666666667,
      "mlt_sector": "DUSK"
    },
    "G18": {
      "time": "2026-05-08 04:58:00+00:00",
      "Hp": 87.87966918945312,
      "B_total": 90.25774383544922,
      "mlt": 19.866666666666667,
      "mlt_sector": "DUSK"
    }
  },
  "detections": {
    "ip_shocks": [],
    "ssc_events": []
  },
  "published_at": "2026-05-08T05:01:03.973410Z"
}