{
  "timestamp": "2026-07-18T12:21:19.190303",
  "l1": {
    "time": "2026-07-18 12:13:00",
    "speed": 336.7,
    "density": 5.43,
    "bt": 3.17,
    "bz_gsm": 1.84,
    "pressure_dyn": 1.02962280896202
  },
  "goes": {
    "G18": {
      "time": "2026-07-18 15:29:00+00:00",
      "Hp": 98.2231674194336,
      "B_total": 102.6320571899414,
      "mlt": 6.336666666666666,
      "mlt_sector": "DAWN"
    },
    "G19": {
      "time": "2026-07-18 15:29:00+00:00",
      "Hp": 112.30209350585938,
      "B_total": 117.34745025634766,
      "mlt": 10.469999999999999,
      "mlt_sector": "NOON"
    }
  },
  "tec": {
    "time": "2026-07-18T15:15:00Z",
    "global_mean_tec": 16.288898956664422,
    "anom_max_abs": 9.340224343119619,
    "anom_rms": 2.234733903951129,
    "threat_belt_anom_mean": -1.8969007784150387,
    "quality_pct": 73.2253086419753
  },
  "detections": {
    "ip_shocks": [],
    "ssc_events": []
  },
  "published_at": "2026-07-18T15:40:50.076090Z"
}