{
  "timestamp": "2026-06-28T20:30:37.673136",
  "l1": {
    "time": "2026-06-28 20:26:00",
    "speed": 463.2,
    "density": 4.01,
    "bt": 3.3,
    "bz_gsm": 1.43,
    "pressure_dyn": 1.4390423215142398
  },
  "goes": {
    "G18": {
      "time": "2026-06-28 20:28:00+00:00",
      "Hp": 107.28741455078125,
      "B_total": 109.4415512084961,
      "mlt": 11.366666666666665,
      "mlt_sector": "NOON"
    },
    "G19": {
      "time": "2026-06-28 20:27:00+00:00",
      "Hp": 100.45133972167969,
      "B_total": 109.34134674072266,
      "mlt": 11.35,
      "mlt_sector": "NOON"
    }
  },
  "tec": {
    "time": "2026-06-28T20:05:00Z",
    "global_mean_tec": 14.764979084906816,
    "anom_max_abs": 10.566928213712206,
    "anom_rms": 1.7737145990048349,
    "threat_belt_anom_mean": 0.4958231280530615,
    "quality_pct": 74.24768518518519
  },
  "detections": {
    "ip_shocks": [],
    "ssc_events": []
  },
  "published_at": "2026-06-28T20:31:23.934983Z"
}