{
  "timestamp": "2026-06-24T21:20:04.235883",
  "l1": {
    "time": "2026-06-24 21:16:00",
    "speed": 581.8,
    "density": 0.2,
    "bt": 11.36,
    "bz_gsm": 7.69,
    "pressure_dyn": 0.1132320896048
  },
  "goes": {
    "G18": {
      "time": "2026-06-24 21:17:00+00:00",
      "Hp": 142.43199157714844,
      "B_total": 143.8178253173828,
      "mlt": 12.183333333333335,
      "mlt_sector": "NOON"
    },
    "G19": {
      "time": "2026-06-24 21:17:00+00:00",
      "Hp": 91.29302215576172,
      "B_total": 108.4168701171875,
      "mlt": 12.183333333333335,
      "mlt_sector": "NOON"
    }
  },
  "tec": {
    "time": "2026-06-24T20:55:00Z",
    "global_mean_tec": 14.759282528214635,
    "anom_max_abs": 26.519724325706633,
    "anom_rms": 2.9344959468794842,
    "threat_belt_anom_mean": 2.3569442808124776,
    "quality_pct": 72.0679012345679
  },
  "detections": {
    "ip_shocks": [],
    "ssc_events": []
  },
  "published_at": "2026-06-24T21:20:44.423954Z"
}