{
  "timestamp": "2026-07-14T22:51:23.239257",
  "l1": {
    "time": "2026-07-14 22:45:00",
    "speed": 406.8,
    "density": 9.26,
    "bt": 8.69,
    "bz_gsm": -2.89,
    "pressure_dyn": 2.5630965593222403
  },
  "goes": {
    "G18": {
      "time": "2026-07-15 02:19:00+00:00",
      "Hp": 103.31682586669922,
      "B_total": 105.67622375488281,
      "mlt": 17.17,
      "mlt_sector": "DUSK"
    },
    "G19": {
      "time": "2026-07-15 02:19:00+00:00",
      "Hp": 76.68701934814453,
      "B_total": 100.39422607421875,
      "mlt": 21.303333333333335,
      "mlt_sector": "NIGHT"
    }
  },
  "tec": {},
  "detections": {
    "ip_shocks": [],
    "ssc_events": []
  },
  "published_at": "2026-07-15T02:30:35.521574Z"
}