{
  "timestamp": "2026-01-22T08:45:04.197200",
  "l1": {
    "time": "2026-01-22 08:43:00",
    "speed": 570.6,
    "density": 2.45,
    "bt": 9.41,
    "bz_gsm": 6.58,
    "pressure_dyn": 1.3342023813132005
  },
  "goes": {
    "G19": {
      "time": "2026-01-22 08:41:00+00:00",
      "Hp": 70.76825714111328,
      "B_total": 77.43461608886719,
      "mlt": 23.583333333333336,
      "mlt_sector": "NIGHT"
    },
    "G18": {
      "time": "2026-01-22 08:42:00+00:00",
      "Hp": 59.60702133178711,
      "B_total": 67.92130279541016,
      "mlt": 23.6,
      "mlt_sector": "NIGHT"
    }
  },
  "detections": {
    "ip_shocks": [],
    "ssc_events": []
  },
  "published_at": "2026-01-22T08:45:44.814129Z"
}