{
  "timestamp": "2026-01-18T23:45:04.426200",
  "l1": {
    "time": "2026-01-18 23:42:00",
    "speed": 502.1,
    "density": 0.05,
    "bt": 7.55,
    "bz_gsm": -3.88,
    "pressure_dyn": 0.021083491808300006
  },
  "goes": {
    "G19": {
      "time": "2026-01-18 23:44:00+00:00",
      "Hp": 60.69466018676758,
      "B_total": 74.11096954345703,
      "mlt": 14.633333333333335,
      "mlt_sector": "NOON"
    },
    "G18": {
      "time": "2026-01-18 23:44:00+00:00",
      "Hp": 91.93354797363281,
      "B_total": 94.76296997070312,
      "mlt": 14.633333333333335,
      "mlt_sector": "NOON"
    }
  },
  "detections": {
    "ip_shocks": [],
    "ssc_events": []
  },
  "published_at": "2026-01-18T23:46:49.182215Z"
}