{
  "timestamp": "2026-05-14T03:30:03.995811",
  "l1": {
    "time": "2026-05-14 03:26:00",
    "speed": 446.3,
    "density": 4.07,
    "bt": 6.96,
    "bz_gsm": 0.59,
    "pressure_dyn": 1.3559393843685803
  },
  "goes": {
    "G19": {
      "time": "2026-05-14 03:28:00+00:00",
      "Hp": 58.175228118896484,
      "B_total": 81.45664978027344,
      "mlt": 18.366666666666667,
      "mlt_sector": "DUSK"
    },
    "G18": {
      "time": "2026-05-14 03:28:00+00:00",
      "Hp": 84.3553695678711,
      "B_total": 86.61031341552734,
      "mlt": 18.366666666666667,
      "mlt_sector": "DUSK"
    }
  },
  "tec": {
    "time": "2026-05-14T03:05:00Z",
    "global_mean_tec": 18.131344182967066,
    "anom_max_abs": 17.166333521275682,
    "anom_rms": 3.3622555337696216,
    "threat_belt_anom_mean": -2.022328690522065,
    "quality_pct": 71.6628086419753
  },
  "detections": {
    "ip_shocks": [],
    "ssc_events": []
  },
  "published_at": "2026-05-14T03:30:53.144001Z"
}