{
  "timestamp": "2026-06-03T21:50:15.892452",
  "l1": {
    "time": "2026-06-03 21:45:00",
    "speed": 448.4,
    "density": 5.24,
    "bt": 9.73,
    "bz_gsm": 5.26,
    "pressure_dyn": 1.76219752636544
  },
  "goes": {
    "G19": {
      "time": "2026-06-03 21:47:00+00:00",
      "Hp": 128.98765563964844,
      "B_total": 131.81817626953125,
      "mlt": 12.683333333333335,
      "mlt_sector": "NOON"
    },
    "G18": {
      "time": "2026-06-03 21:48:00+00:00",
      "Hp": 107.9273910522461,
      "B_total": 114.22911834716797,
      "mlt": 12.700000000000001,
      "mlt_sector": "NOON"
    }
  },
  "tec": {
    "time": "2026-06-03T21:25:00Z",
    "global_mean_tec": 16.7108359089705,
    "anom_max_abs": 12.541400124992805,
    "anom_rms": 2.700548086864503,
    "threat_belt_anom_mean": 0.4096576707173268,
    "quality_pct": 74.55632716049382
  },
  "detections": {
    "ip_shocks": [],
    "ssc_events": []
  },
  "published_at": "2026-06-03T21:50:59.743164Z"
}