{
  "timestamp": "2026-05-10T03:30:15.079030",
  "l1": {
    "time": "2026-05-10 03:28:00",
    "speed": 427.8,
    "density": 3.88,
    "bt": 3.41,
    "bz_gsm": 2.57,
    "pressure_dyn": 1.1876962315939201
  },
  "goes": {
    "G19": {
      "time": "2026-05-10 03:28:00+00:00",
      "Hp": 84.51398468017578,
      "B_total": 96.59502410888672,
      "mlt": 18.366666666666667,
      "mlt_sector": "DUSK"
    },
    "G18": {
      "time": "2026-05-10 03:27:00+00:00",
      "Hp": 94.9281234741211,
      "B_total": 97.42025756835938,
      "mlt": 18.35,
      "mlt_sector": "DUSK"
    }
  },
  "detections": {
    "ip_shocks": [],
    "ssc_events": []
  },
  "published_at": "2026-05-10T03:31:06.669356Z"
}