{
  "timestamp": "2026-07-23T06:51:25.304397",
  "l1": {
    "time": "2026-07-23 06:43:00",
    "speed": 587.3,
    "density": 7.03,
    "bt": 9.81,
    "bz_gsm": -5.14,
    "pressure_dyn": 4.055714908067619
  },
  "goes": {
    "G18": {
      "time": "2026-07-23 10:39:00+00:00",
      "Hp": 76.51655578613281,
      "B_total": 88.97808837890625,
      "mlt": 1.5033333333333339,
      "mlt_sector": "NIGHT"
    },
    "G19": {
      "time": "2026-07-23 10:40:00+00:00",
      "Hp": 53.883262634277344,
      "B_total": 68.75977325439453,
      "mlt": 5.653333333333332,
      "mlt_sector": "DAWN"
    }
  },
  "tec": {
    "time": "2026-07-23T10:15:00Z",
    "global_mean_tec": 20.64143500781273,
    "anom_max_abs": 11.625030800254223,
    "anom_rms": 2.8324528221396883,
    "threat_belt_anom_mean": 1.8618421554705133,
    "quality_pct": 76.83256172839506
  },
  "detections": {
    "ip_shocks": [],
    "ssc_events": []
  },
  "published_at": "2026-07-23T10:50:58.894474Z"
}