{
  "timestamp": "2026-05-28T22:50:16.669778",
  "l1": {
    "time": "2026-05-28 22:47:00",
    "speed": 435.2,
    "density": 3.31,
    "bt": 5.32,
    "bz_gsm": -3.47,
    "pressure_dyn": 1.04857104154624
  },
  "goes": {
    "G19": {
      "time": "2026-05-28 22:48:00+00:00",
      "Hp": 83.10144805908203,
      "B_total": 100.3215560913086,
      "mlt": 13.700000000000001,
      "mlt_sector": "NOON"
    }
  },
  "tec": {
    "time": "2026-05-28T22:25:00Z",
    "global_mean_tec": 17.769107257195717,
    "anom_max_abs": 13.992174868755697,
    "anom_rms": 2.7175237732192787,
    "threat_belt_anom_mean": 1.0626425096896241,
    "quality_pct": 79.4945987654321
  },
  "detections": {
    "ip_shocks": [],
    "ssc_events": []
  },
  "published_at": "2026-05-28T22:51:20.386953Z"
}