{
  "timestamp": "2026-06-03T01:00:39.387121",
  "l1": {
    "time": "2026-06-03 00:56:00",
    "speed": 386.3,
    "density": 3.44,
    "bt": 7.67,
    "bz_gsm": -4.83,
    "pressure_dyn": 0.85861792597136
  },
  "goes": {
    "G19": {
      "time": "2026-06-03 00:58:00+00:00",
      "Hp": 74.09151458740234,
      "B_total": 97.81694030761719,
      "mlt": 15.866666666666667,
      "mlt_sector": "DUSK"
    },
    "G18": {
      "time": "2026-06-03 00:58:00+00:00",
      "Hp": 73.21825408935547,
      "B_total": 77.37174224853516,
      "mlt": 15.866666666666667,
      "mlt_sector": "DUSK"
    }
  },
  "tec": {
    "time": "2026-06-03T00:25:00Z",
    "global_mean_tec": 16.527727054989555,
    "anom_max_abs": 16.5846545682638,
    "anom_rms": 2.8098138325585698,
    "threat_belt_anom_mean": 0.5383799624104694,
    "quality_pct": 73.2253086419753
  },
  "detections": {
    "ip_shocks": [],
    "ssc_events": []
  },
  "published_at": "2026-06-03T01:01:32.776608Z"
}