{
  "timestamp": "2026-07-03T03:40:04.126096",
  "l1": {},
  "goes": {
    "G19": {
      "time": "2026-07-03 03:36:00+00:00",
      "Hp": 86.84788513183594,
      "B_total": 97.92155456542969,
      "mlt": 18.5,
      "mlt_sector": "DUSK"
    }
  },
  "tec": {
    "time": "2026-07-03T03:15:00Z",
    "global_mean_tec": 15.434856798089383,
    "anom_max_abs": 12.335363646830444,
    "anom_rms": 1.4447015448350269,
    "threat_belt_anom_mean": 0.3008336445946217,
    "quality_pct": 70.89120370370371
  },
  "detections": {
    "ip_shocks": [],
    "ssc_events": []
  },
  "published_at": "2026-07-03T03:40:06.663368Z"
}