{
  "timestamp": "2026-05-24T17:30:23.907619",
  "l1": {
    "time": "2026-05-24 17:27:00",
    "speed": 287.7,
    "density": 6.51,
    "bt": 5.15,
    "bz_gsm": -3.1,
    "pressure_dyn": 0.90126562034754
  },
  "goes": {
    "G19": {
      "time": "2026-05-24 17:28:00+00:00",
      "Hp": 122.9897689819336,
      "B_total": 127.47635650634766,
      "mlt": 8.366666666666665,
      "mlt_sector": "DAWN"
    },
    "G18": {
      "time": "2026-05-24 17:29:00+00:00",
      "Hp": 117.015625,
      "B_total": 120.20088195800781,
      "mlt": 8.383333333333335,
      "mlt_sector": "DAWN"
    }
  },
  "tec": {
    "time": "2026-05-24T17:05:00Z",
    "global_mean_tec": 17.491361771510558,
    "anom_max_abs": 19.683567517319215,
    "anom_rms": 3.4690421643650553,
    "threat_belt_anom_mean": 2.5304928391854395,
    "quality_pct": 73.20601851851852
  },
  "detections": {
    "ip_shocks": [],
    "ssc_events": []
  },
  "published_at": "2026-05-24T17:31:18.883452Z"
}