{
  "timestamp": "2026-06-04T06:50:16.461223",
  "l1": {
    "time": "2026-06-04 06:47:00",
    "speed": 379.4,
    "density": 1.04,
    "bt": 6.59,
    "bz_gsm": 1.03,
    "pressure_dyn": 0.25039178999744
  },
  "goes": {
    "G19": {
      "time": "2026-06-04 06:48:00+00:00",
      "Hp": 62.284584045410156,
      "B_total": 67.21129608154297,
      "mlt": 21.7,
      "mlt_sector": "NIGHT"
    },
    "G18": {
      "time": "2026-06-04 06:49:00+00:00",
      "Hp": 64.478271484375,
      "B_total": 86.74342346191406,
      "mlt": 21.71666666666667,
      "mlt_sector": "NIGHT"
    }
  },
  "tec": {
    "time": "2026-06-04T06:25:00Z",
    "global_mean_tec": 18.742608189108285,
    "anom_max_abs": 15.268681566950455,
    "anom_rms": 2.4489559541412365,
    "threat_belt_anom_mean": 2.027232051424187,
    "quality_pct": 73.39891975308642
  },
  "detections": {
    "ip_shocks": [],
    "ssc_events": []
  },
  "published_at": "2026-06-04T06:51:12.514079Z"
}