{
  "timestamp": "2026-06-10T17:20:04.063794",
  "l1": {
    "time": "2026-06-10 17:16:00",
    "speed": 394.1,
    "density": 10.8,
    "bt": 5.43,
    "bz_gsm": 4.66,
    "pressure_dyn": 2.8056191530248005
  },
  "goes": {
    "G18": {
      "time": "2026-06-10 17:18:00+00:00",
      "Hp": 107.35954284667969,
      "B_total": 111.57374572753906,
      "mlt": 8.200000000000001,
      "mlt_sector": "DAWN"
    },
    "G19": {
      "time": "2026-06-10 17:17:00+00:00",
      "Hp": 120.46282196044922,
      "B_total": 126.41020202636719,
      "mlt": 8.183333333333335,
      "mlt_sector": "DAWN"
    }
  },
  "tec": {
    "time": "2026-06-10T16:45:00Z",
    "global_mean_tec": 15.607251437303235,
    "anom_max_abs": 14.461945714497926,
    "anom_rms": 3.029391980441859,
    "threat_belt_anom_mean": -0.6332017035724928,
    "quality_pct": 73.12885802469135
  },
  "detections": {
    "ip_shocks": [],
    "ssc_events": []
  },
  "published_at": "2026-06-10T17:20:45.943549Z"
}