{
  "timestamp": "2026-01-13T14:30:03.971273",
  "l1": {
    "time": "2026-01-13 14:13:00",
    "speed": 580.2,
    "density": 0.3,
    "bt": 4.89,
    "bz_gsm": -2.98,
    "pressure_dyn": 0.16891522503120002
  },
  "goes": {
    "G19": {
      "time": "2026-01-13 14:28:00+00:00",
      "Hp": 92.44440460205078,
      "B_total": 101.00931549072266,
      "mlt": 5.366666666666667,
      "mlt_sector": "DAWN"
    },
    "G18": {
      "time": "2026-01-13 14:28:00+00:00",
      "Hp": 85.03826141357422,
      "B_total": 87.60520935058594,
      "mlt": 5.366666666666667,
      "mlt_sector": "DAWN"
    }
  },
  "detections": {
    "ip_shocks": [],
    "ssc_events": []
  },
  "published_at": "2026-01-13T14:30:38.579517Z"
}