{
  "timestamp": "2026-06-10T09:50:04.175902",
  "l1": {
    "time": "2026-06-10 09:46:00",
    "speed": 392.8,
    "density": 8.36,
    "bt": 5.25,
    "bz_gsm": -1.69,
    "pressure_dyn": 2.1574529240422398
  },
  "goes": {
    "G19": {
      "time": "2026-06-10 09:48:00+00:00",
      "Hp": 58.95555114746094,
      "B_total": 85.62394714355469,
      "mlt": 0.7000000000000011,
      "mlt_sector": "NIGHT"
    },
    "G18": {
      "time": "2026-06-10 09:49:00+00:00",
      "Hp": 63.02577590942383,
      "B_total": 99.03968811035156,
      "mlt": 0.7166666666666668,
      "mlt_sector": "NIGHT"
    }
  },
  "tec": {
    "time": "2026-06-10T09:25:00Z",
    "global_mean_tec": 17.130841189618423,
    "anom_max_abs": 13.562419104714692,
    "anom_rms": 3.2531432005937346,
    "threat_belt_anom_mean": -1.7607693927233523,
    "quality_pct": 73.4375
  },
  "detections": {
    "ip_shocks": [],
    "ssc_events": []
  },
  "published_at": "2026-06-10T09:51:18.234564Z"
}