{
  "timestamp": "2026-06-11T02:10:22.222787",
  "l1": {
    "time": "2026-06-11 02:06:00",
    "speed": 394.1,
    "density": 10.43,
    "bt": 8.98,
    "bz_gsm": 8.0,
    "pressure_dyn": 2.7095007190785805
  },
  "goes": {
    "G18": {
      "time": "2026-06-11 02:08:00+00:00",
      "Hp": 108.95331573486328,
      "B_total": 111.21883392333984,
      "mlt": 17.03333333333333,
      "mlt_sector": "DUSK"
    },
    "G19": {
      "time": "2026-06-11 02:08:00+00:00",
      "Hp": 82.67862701416016,
      "B_total": 100.00902557373047,
      "mlt": 17.03333333333333,
      "mlt_sector": "DUSK"
    }
  },
  "tec": {
    "time": "2026-06-11T01:45:00Z",
    "global_mean_tec": 15.596899419344762,
    "anom_max_abs": 14.511093321339146,
    "anom_rms": 3.1380232357277484,
    "threat_belt_anom_mean": -1.0701474739699708,
    "quality_pct": 73.10956790123457
  },
  "detections": {
    "ip_shocks": [],
    "ssc_events": []
  },
  "published_at": "2026-06-11T02:10:59.927069Z"
}