{
  "timestamp": "2026-01-16T21:30:04.024312",
  "l1": {
    "time": "2026-01-16 21:28:00",
    "speed": 644.3,
    "density": 2.18,
    "bt": 10.95,
    "bz_gsm": -2.6,
    "pressure_dyn": 1.51364785136732
  },
  "goes": {
    "G19": {
      "time": "2026-01-16 21:28:00+00:00",
      "Hp": 81.1384506225586,
      "B_total": 85.23892974853516,
      "mlt": 12.366666666666665,
      "mlt_sector": "NOON"
    },
    "G18": {
      "time": "2026-01-16 21:28:00+00:00",
      "Hp": 123.50666809082031,
      "B_total": 125.95893859863281,
      "mlt": 12.366666666666665,
      "mlt_sector": "NOON"
    }
  },
  "detections": {
    "ip_shocks": [],
    "ssc_events": []
  },
  "published_at": "2026-01-16T21:31:30.723538Z"
}