{
  "timestamp": "2026-01-11T23:30:04.279663",
  "l1": {
    "time": "2026-01-11 23:27:00",
    "speed": 543.8,
    "density": 0.8,
    "bt": 8.03,
    "bz_gsm": -5.44,
    "pressure_dyn": 0.3956949301952
  },
  "goes": {
    "G19": {
      "time": "2026-01-11 23:28:00+00:00",
      "Hp": 69.69491577148438,
      "B_total": 91.64930725097656,
      "mlt": 14.366666666666665,
      "mlt_sector": "NOON"
    },
    "G18": {
      "time": "2026-01-11 23:28:00+00:00",
      "Hp": 91.93091583251953,
      "B_total": 95.35346221923828,
      "mlt": 14.366666666666665,
      "mlt_sector": "NOON"
    }
  },
  "detections": {
    "ip_shocks": [],
    "ssc_events": []
  },
  "published_at": "2026-01-11T23:30:54.770668Z"
}