{
  "timestamp": "2026-01-15T11:30:04.074069",
  "l1": {
    "time": "2026-01-15 11:27:00",
    "speed": 620.6,
    "density": 0.1,
    "bt": 5.28,
    "bz_gsm": 1.36,
    "pressure_dyn": 0.06441924565360002
  },
  "goes": {
    "G19": {
      "time": "2026-01-15 11:27:00+00:00",
      "Hp": 93.92108917236328,
      "B_total": 99.70179748535156,
      "mlt": 2.3499999999999996,
      "mlt_sector": "NIGHT"
    },
    "G18": {
      "time": "2026-01-15 11:27:00+00:00",
      "Hp": 58.64193344116211,
      "B_total": 60.677879333496094,
      "mlt": 2.3499999999999996,
      "mlt_sector": "NIGHT"
    }
  },
  "detections": {
    "ip_shocks": [],
    "ssc_events": []
  },
  "published_at": "2026-01-15T11:30:57.515622Z"
}