{
  "timestamp": "2026-01-17T16:00:04.013736",
  "l1": {
    "time": "2026-01-17 15:57:00",
    "speed": 703.3,
    "density": 0.72,
    "bt": 8.27,
    "bz_gsm": -0.89,
    "pressure_dyn": 0.5956701311620799
  },
  "goes": {
    "G19": {
      "time": "2026-01-17 15:58:00+00:00",
      "Hp": 112.7545166015625,
      "B_total": 117.83114624023438,
      "mlt": 6.866666666666667,
      "mlt_sector": "DAWN"
    },
    "G18": {
      "time": "2026-01-17 15:57:00+00:00",
      "Hp": 94.59819793701172,
      "B_total": 96.90543365478516,
      "mlt": 6.85,
      "mlt_sector": "DAWN"
    }
  },
  "detections": {
    "ip_shocks": [],
    "ssc_events": []
  },
  "published_at": "2026-01-17T16:01:08.285803Z"
}