{
  "timestamp": "2026-05-07T11:00:11.542189",
  "l1": {
    "time": "2026-05-07 10:57:00",
    "speed": 344.8,
    "density": 3.86,
    "bt": 5.27,
    "bz_gsm": 1.9,
    "pressure_dyn": 0.76756278758144
  },
  "goes": {
    "G19": {
      "time": "2026-05-07 10:58:00+00:00",
      "Hp": 100.18331909179688,
      "B_total": 109.39170837402344,
      "mlt": 1.8666666666666671,
      "mlt_sector": "NIGHT"
    },
    "G18": {
      "time": "2026-05-07 10:58:00+00:00",
      "Hp": 89.14642333984375,
      "B_total": 94.30359649658203,
      "mlt": 1.8666666666666671,
      "mlt_sector": "NIGHT"
    }
  },
  "detections": {
    "ip_shocks": [],
    "ssc_events": []
  },
  "published_at": "2026-05-07T11:01:34.275524Z"
}