{
  "timestamp": "2026-01-24T11:30:05.237322",
  "l1": {
    "time": "2026-01-24 11:27:00",
    "speed": 517.3,
    "density": 1.56,
    "bt": 6.6,
    "bz_gsm": 0.3,
    "pressure_dyn": 0.69823505302824
  },
  "goes": {
    "G19": {
      "time": "2026-01-24 11:27:00+00:00",
      "Hp": 88.67475128173828,
      "B_total": 101.04322052001953,
      "mlt": 2.3499999999999996,
      "mlt_sector": "NIGHT"
    },
    "G18": {
      "time": "2026-01-24 11:28:00+00:00",
      "Hp": 75.895751953125,
      "B_total": 78.59355163574219,
      "mlt": 2.366666666666667,
      "mlt_sector": "NIGHT"
    }
  },
  "detections": {
    "ip_shocks": [],
    "ssc_events": []
  },
  "published_at": "2026-01-24T11:31:07.963238Z"
}